autoenhance/__init__.py
autoenhance/api_client.py
autoenhance/api_response.py
autoenhance/configuration.py
autoenhance/exceptions.py
autoenhance/py.typed
autoenhance/rest.py
autoenhance/api/__init__.py
autoenhance/api/brackets_api.py
autoenhance/api/images_api.py
autoenhance/api/orders_api.py
autoenhance/models/__init__.py
autoenhance/models/bracke_createdt_out.py
autoenhance/models/bracket_in.py
autoenhance/models/bracket_out.py
autoenhance/models/http_error.py
autoenhance/models/image_created_out.py
autoenhance/models/image_created_out_finetune_settings.py
autoenhance/models/image_in.py
autoenhance/models/image_in_update.py
autoenhance/models/image_out.py
autoenhance/models/order_brackets_out.py
autoenhance/models/order_hdr_merge.py
autoenhance/models/order_hdr_process_in.py
autoenhance/models/order_hdr_process_out.py
autoenhance/models/order_image_in.py
autoenhance/models/order_in.py
autoenhance/models/order_out.py
autoenhance/models/orders_out.py
autoenhance/models/pagination.py
autoenhance/models/report_in.py
autoenhance/models/validation_error.py
autoenhance/models/validation_error_detail.py
autoenhance/models/validation_error_detail_location.py
autoenhance-1.1.0.dist-info/METADATA
autoenhance-1.1.0.dist-info/WHEEL
autoenhance-1.1.0.dist-info/top_level.txt
autoenhance-1.1.0.dist-info/RECORD
